SNL_Auditor
