Metadata-Version: 1.0
Name: SNL-Auditor
Version: 0.0.3
Summary: Ferramenta para auditar o Mandate 800
Home-page: https://github.com/celsoxavier/Auditor
Author: Celso Xavier
Author-email: celso.xavier@sonangol.co.ao
License: MIT
Platform: UNKNOWN
